dadosfera/__init__.py
dadosfera/components/__init__.py
dadosfera/components/brand.py
dadosfera/components/generate_pdf_javascript.py
dadosfera/components/hamburger_menu.py
dadosfera/components/storage.py
dadosfera/consts.py
dadosfera/loaders/__init__.py
dadosfera/loaders/whisper.py
dadosfera/services/__init__.py
dadosfera/services/apify.py
dadosfera/services/autodrive.py
dadosfera/services/deeplake.py
dadosfera/services/email_notification.py
dadosfera/services/email_sender/EmailSender Documentation.md
dadosfera/services/email_sender/__init__.py
dadosfera/services/email_sender/email_sender.py
dadosfera/services/email_sender/renders.py
dadosfera/services/google_chat.py
dadosfera/services/maestro/__init__.py
dadosfera/services/maestro/connections.py
dadosfera/services/maestro/dashboards.py
dadosfera/services/maestro/data_assets.py
dadosfera/services/maestro/maestro_config.py
dadosfera/services/maestro/pipelines.py
dadosfera/services/maestro/users.py
dadosfera/services/metabase.py
dadosfera/services/openai.py
dadosfera/services/platform_api.py
dadosfera/services/s3.py
dadosfera/services/scraping.py
dadosfera/services/secretsmanager.py
dadosfera/services/snowflake.py
dadosfera/services/streamlit.py
dadosfera/services/teams_chat.py
dadosfera/utils/__init__.py
dadosfera/utils/consts.py
dadosfera/utils/file.py
dadosfera-1.22.0.dist-info/LICENSE
dadosfera-1.22.0.dist-info/METADATA
dadosfera-1.22.0.dist-info/WHEEL
dadosfera-1.22.0.dist-info/RECORD
