Metadata-Version: 2.1
Name: dadosfera
Version: 1.22.0
Summary: Biblioteca Dadosfera para processamento e análise de dados
Home-page: https://github.com/dadosfera/dadosfera-library
License: MIT
Keywords: data,analysis,processing,dadosfera
Author: rafael
Author-email: rafael.santana@datasprints.com
Requires-Python: >=3.6.2,<4.0
Classifier: Development Status :: 4 - Beta
Classifier: Intended Audience :: Developers
Classifier: License :: OSI Approved :: MIT License
Classifier: Programming Language :: Python :: 3
Classifier: Programming Language :: Python :: 3.7
Classifier: Programming Language :: Python :: 3.8
Classifier: Programming Language :: Python :: 3.9
Classifier: Programming Language :: Python :: 3.10
Classifier: Programming Language :: Python :: 3.11
Classifier: Programming Language :: Python :: 3.12
Classifier: Programming Language :: Python :: 3.13
Classifier: Programming Language :: Python :: 3.6
Requires-Dist: PyYAML (>=6.0,<7.0)
Requires-Dist: Unidecode (>=1.3.2,<2.0.0)
Requires-Dist: numpy (<2)
Requires-Dist: py4j (>=0.10.9,<0.11.0)
Requires-Dist: s3fs (==0.4.2)
Project-URL: Documentation, https://dadosfera-library.readthedocs.io
Project-URL: Repository, https://github.com/dadosfera/dadosfera-library
